{"results": [{"choreo": "slmrpggmtjroqtos", "value": 0.442510893246}, {"choreo": "eccjcgnppssorrnm", "value": 0.405991285403}, {"choreo": "tfbgrdmaggqdspdf", "value": 0.364938201776}, {"choreo": "olpfbstarprbgaes", "value": 0.354043829408}, {"choreo": "fkpoijjicqfbphcq", "value": 0.329597069597}, {"choreo": "fsmfdnharhhjjbbo", "value": 0.326004273504}, {"choreo": "nolpdjcclmdbjcfg", "value": 0.324810744811}, {"choreo": "blhjohmimghdblqc", "value": 0.313948412698}, {"choreo": "tpjcdmrnkijfgahf", "value": 0.308905228758}, {"choreo": "tkfdammhodflhgbe", "value": 0.246153846154}, {"choreo": "tgjglstnskkkjajt", "value": 0.396356029591}, {"choreo": "gtjmfsqtqrdkmmpo", "value": 0.390377762216}, {"choreo": "mkldlnkrssfpjpgl", "value": 0.363077342048}, {"choreo": "rkdmgpsopbnqldpp", "value": 0.353227902272}, {"choreo": "bgmiimlrlptmaghi", "value": 0.345071554263}, {"choreo": "lrafpnkakilahllk", "value": 0.322808302808}, {"choreo": "pnfhhtcdihnmanqi", "value": 0.320714285714}, {"choreo": "dgjtcjtlqaabbidc", "value": 0.317514005602}, {"choreo": "gjpkcnmhkhfemedg", "value": 0.304036935287}, {"choreo": "qebelllbblafieel", "value": 0.284328079328}, {"choreo": "ogchrtpqskqcpkof", "value": 0.40999928333906666}, {"choreo": "qgpksnqhctsgbtgn", "value": 0.38989379084967324}, {"choreo": "hppptimspplrkjpo", "value": 0.38068082788671026}, {"choreo": "pmmhqmrhfitmsacd", "value": 0.34562908496732025}, {"choreo": "rplonitdhrrbfsld", "value": 0.333739884842826}, {"choreo": "mfrphtdqctkejfmr", "value": 0.33360760971055087}, {"choreo": "hanjnamlnkhkheto", "value": 0.3227869352869353}, {"choreo": "qldlrkjgbprfneeb", "value": 0.31152894491129784}, {"choreo": "jsdpbjnhheqflian", "value": 0.2662581699346405}, {"choreo": "bgidghakfeekicln", "value": 0.19142928966458375}, {"choreo": "gftfiojjtsgcspgs", "value": 0.41410507792860746}, {"choreo": "eqfsollsscgljsro", "value": 0.39686232612703193}, {"choreo": "ljjthgooegirrhol", "value": 0.38248626373626377}, {"choreo": "mjgasgknogqmeaig", "value": 0.3410714285714285}, {"choreo": "tcgkbtjmqsflleen", "value": 0.33343868249054}, {"choreo": "jamdtjbgtorqrfio", "value": 0.3314993775287893}, {"choreo": "gbtppaaiclspgidb", "value": 0.32056605975723623}, {"choreo": "htlqbacrmecsekhe", "value": 0.31686858076563956}, {"choreo": "bpqaeeefaksdakmh", "value": 0.2657581878905408}, {"choreo": "acfnrlkmddegbmes", "value": 0.2619859225741578}, {"choreo": "cnpfjjqtgdgtpgps", "value": 0.40603443941679235}, {"choreo": "tgriltaoagjlomsq", "value": 0.3982172342621259}, {"choreo": "ihmttfpplohigmrf", "value": 0.384795751633987}, {"choreo": "kcpjamchcrcsfhns", "value": 0.3580964052287582}, {"choreo": "sobrirolpptkmrhj", "value": 0.35267973856209145}, {"choreo": "tnoenmkgbfmejbkf", "value": 0.33880261078790486}, {"choreo": "bhtifebfskmqcrfj", "value": 0.32221061231510145}, {"choreo": "ojjjesafbradeced", "value": 0.3090991198344139}, {"choreo": "mprfhebjgbiclaat", "value": 0.29553104575163397}, {"choreo": "okiffrlldagjlpei", "value": 0.2832159915248151}, {"choreo": "rtpmjsefrgfcjefo", "value": 0.40206760774485234}, {"choreo": "rsmsgmfohemecest", "value": 0.3921047008547009}, {"choreo": "iffmqfpnfepeqgqc", "value": 0.35876831501831496}, {"choreo": "nttbjbfnlbitcghs", "value": 0.3494619719232722}, {"choreo": "rtriirbcrddrhsqk", "value": 0.3402951052215758}, {"choreo": "pijgeoaoitqfhjrk", "value": 0.33766468868249055}, {"choreo": "dmacnknshhsbgpqq", "value": 0.31240079365079365}, {"choreo": "ifjerblnqaldisqe", "value": 0.2862330316742081}, {"choreo": "ehmcakakjjngdmmb", "value": 0.25369963369963366}, {"choreo": "falomiafckdlkbdr", "value": 0.24512820512820516}, {"choreo": "qnptosgthilccjpj", "value": 0.39731682146542824}, {"choreo": "lnmmdnrqkqpqmlgm", "value": 0.3768727106227106}, {"choreo": "kkjqqhbcbrhqbqar", "value": 0.3544505494505494}, {"choreo": "rfmertslqpishafe", "value": 0.3428212074303405}, {"choreo": "qddlgcqkgckkqahp", "value": 0.32724053724053725}, {"choreo": "ngcidhlscgolkjmc", "value": 0.31906629318394025}, {"choreo": "asheoiqocphhndmn", "value": 0.30440476190476196}, {"choreo": "bgtpnhnetakrlord", "value": 0.28784936196700894}, {"choreo": "ombkbpqmemaipasd", "value": 0.26833842083842085}, {"choreo": "oocldbmppikfgdqe", "value": 0.2569642857142857}]}